arduino_iot_cloud/__init__.py
arduino_iot_cloud/_version.py
arduino_iot_cloud/ucloud.py
arduino_iot_cloud/umqtt.py
arduino_iot_cloud/ussl.py
arduino_iot_cloud-1.4.1.dist-info/LICENSE
arduino_iot_cloud-1.4.1.dist-info/METADATA
arduino_iot_cloud-1.4.1.dist-info/WHEEL
arduino_iot_cloud-1.4.1.dist-info/top_level.txt
arduino_iot_cloud-1.4.1.dist-info/RECORD
