Metadata-Version: 2.2
Name: arduino_iot_cloud
Version: 1.4.1
Summary: Arduino IoT Cloud Python client
Author-email: Ibrahim Abdelkader <i.abdelkader@arduino.cc>
Project-URL: Homepage, https://github.com/arduino/arduino-iot-cloud-py
Project-URL: Bug Tracker, https://github.com/arduino/arduino-iot-cloud-py/issues
Classifier: Programming Language :: Python :: 3
Classifier: Topic :: Software Development :: Embedded Systems
Classifier: Operating System :: OS Independent
Classifier: License :: OSI Approved :: Mozilla Public License 2.0 (MPL 2.0)
Requires-Python: >=3.8
License-File: LICENSE
Requires-Dist: cbor2>=5.6.2
Requires-Dist: micropython-senml>=0.1.1
